bencherscaffold/__init__.py
bencherscaffold/client.py
bencherscaffold/protoclasses/__init__.py
bencherscaffold/protoclasses/bencher_pb2.py
bencherscaffold/protoclasses/bencher_pb2.pyi
bencherscaffold/protoclasses/bencher_pb2_grpc.py
bencherscaffold/protoclasses/grcp_service.py
bencherscaffold/protoclasses/second_level_services_pb2.py
bencherscaffold/protoclasses/second_level_services_pb2.pyi
bencherscaffold/protoclasses/second_level_services_pb2_grpc.py
bencherscaffold/protos/bencher.proto
bencherscaffold/protos/second_level_services.proto
bencherscaffold-0.3.4.dist-info/METADATA
bencherscaffold-0.3.4.dist-info/WHEEL
bencherscaffold-0.3.4.dist-info/RECORD
